aiosocksy/__init__.py
aiosocksy/connector.py
aiosocksy/constants.py
aiosocksy/errors.py
aiosocksy/helpers.py
aiosocksy/protocols.py
aiosocksy/test_utils.py
aiosocksy-0.1.1.dist-info/METADATA
aiosocksy-0.1.1.dist-info/RECORD
aiosocksy-0.1.1.dist-info/WHEEL
aiosocksy-0.1.1.dist-info/top_level.txt
